salomon/__init__.py
salomon/impl/CopyModelPackage.py
salomon/impl/__init__.py
salomon/impl/s3_helper.py
salomon-0.0.8.dist-info/LICENSE
salomon-0.0.8.dist-info/METADATA
salomon-0.0.8.dist-info/WHEEL
salomon-0.0.8.dist-info/top_level.txt
salomon-0.0.8.dist-info/RECORD
