Metadata-Version: 2.1
Name: salomon
Version: 0.0.8
Summary: Sage mAker modeL cOpy froM One account to aNother
Home-page: https://github.com/bezalelsoft/salomon
Author: bezalelsoft
Project-URL: Bug Tracker, https://github.com/bezalelsoft/salomon/issues
Classifier: Programming Language :: Python :: 3
Classifier: License :: OSI Approved :: MIT License
Classifier: Operating System :: OS Independent
Requires-Python: >=3.7
License-File: LICENSE
Requires-Dist: boto3
Requires-Dist: docker (<6.0,>=5.0.3)
